{
  "id": "dreadmaps",
  "title": "🌑 DreadMaps Premium Map Collection",
  "description": "A collection of my Foundry enabled content",
  "version": "2.0.0",
  "compatibility": {
    "minimum": 10,
    "verified": "10.286"
  },
  "authors": [
    {
      "name": "DreadMaps",
      "url": "https://patreon.com/DreadMaps",
      "email": "dreadmaps@protonmail.com",
      "discord": "Dread Maps#8058"
    }
  ],
 "relationships": {
    "requires": [
      {
        "id": "compendium-folders",
        "type": "module",
        "manifest": "https://raw.githubusercontent.com/earlSt1/vtt-compendium-folders/10x-update/module.json"
      },
      {
	"id": "stairways",
	"type": "module",
	"manifest": "https://gitlab.com/SWW13/foundryvtt-stairways/-/raw/development/module.json"
      }
    ]
  },
  "packs": [
    {
	  "name": "maps",
	  "label": "DreadMaps Map Collection",
	  "path": "packs/dreadmaps.db",
	  "type": "Scene",
	  "private": false
    },
    {
      "label": "DreadMaps Audio Collection",
      "name": "dreadmaps-audio-collection",
      "path": "packs/dreadmaps-audio-collection.db",
      "type": "Playlist",
      "private": false
    }
  ],
  "url": "https://www.patreon.com/dreadmaps",
  "manifest": "https://raw.githubusercontent.com/dreadmaps/map-collection/10x/module.json",
  "download": "https://www.dropbox.com/s/6524vf0ndz1roy2/dreadmaps_10x.zip?dl=1"
}
